.gitignore
LICENSE
README.md
pyproject.toml
requirements.txt
setup.cfg
setup.py
examples/Example_CIR_MLE.py
examples/Example_TimeDependent_MLE.py
examples/RealDataExample_CIR_Fit_Interest.py
examples/RealDataExample_CKLS_Fit_Interest.py
pymle/__init__.py
pymle/core/Model.py
pymle/core/TransitionDensity.py
pymle/core/__init__.py
pymle/ctmc/CTMCEstimator.py
pymle/ctmc/Generator1D.py
pymle/ctmc/StateSpace.py
pymle/ctmc/__init__.py
pymle/ctmc/utility/__init__.py
pymle/data/10yrCMrate.csv
pymle/data/FX_EUR_USD.csv
pymle/data/VIX.csv
pymle/data/__init__.py
pymle/data/loader.py
pymle/fit/AnalyticalMLE.py
pymle/fit/Estimator.py
pymle/fit/LikelihoodEstimator.py
pymle/fit/Minimizer.py
pymle/fit/__init__.py
pymle/models/AitSahalia96.py
pymle/models/BrownianMotion.py
pymle/models/CEV.py
pymle/models/CIR.py
pymle/models/CKLS.py
pymle/models/FellerRoot.py
pymle/models/GeometricBM.py
pymle/models/Hyperbolic.py
pymle/models/Hyperbolic2.py
pymle/models/IGBM.py
pymle/models/Jacobi.py
pymle/models/LinearSDE1.py
pymle/models/LinearSDE2.py
pymle/models/Logistic.py
pymle/models/ModifiedCIR.py
pymle/models/NonLinearSDE.py
pymle/models/OrnsteinUhlenbeck.py
pymle/models/Pearson.py
pymle/models/PeralVerhulst.py
pymle/models/RadialOU.py
pymle/models/Threehalf.py
pymle/models/__init__.py
pymle/sim/Simulator1D.py
pymle/sim/Stepper.py
pymle/sim/__init__.py
pymle_diffusion.egg-info/PKG-INFO
pymle_diffusion.egg-info/SOURCES.txt
pymle_diffusion.egg-info/dependency_links.txt
pymle_diffusion.egg-info/not-zip-safe
pymle_diffusion.egg-info/requires.txt
pymle_diffusion.egg-info/top_level.txt
tests/__init__.py
tests/test_runner.py
tests/fit/Test_AnalyticalMLE.py
tests/fit/__init__.py
tests/fit/suite.py
tests/models/Test_CEV.py
tests/models/__init__.py
tests/models/suite.py