Metadata-Version: 1.2
Name: pymle-diffusion
Version: 0.0.9
Summary: Maximum Likelihood Estimation (MLE) and simulation for SDE
Home-page: https://github.com/jkirkby3/pymle
Author: Justin Lars Kirkby
Author-email: jkirkby33@gmail.com
License: MIT
Keywords: sde mle maximum likelihood difussion estimation simulation
Platform: UNKNOWN
Classifier: Development Status :: 3 - Alpha
Classifier: License :: OSI Approved :: MIT License
Classifier: Programming Language :: Python :: 3.7
Classifier: Topic :: Scientific/Engineering 
Classifier: Operating System :: OS Independent
Requires-Python: >=3.7
